provlake/__init__.py
provlake/capture/__init__.py
provlake/capture/activity_capture.py
provlake/data_extraction/__init__.py
provlake/data_extraction/file_extraction.py
provlake/model/__init__.py
provlake/model/activity_prov_obj.py
provlake/model/cycle_prov_obj.py
provlake/model/data_store_prov_obj.py
provlake/model/query_obj.py
provlake/model/task_prov_obj.py
provlake/model/workflow_prov_obj.py
provlake/persistence/__init__.py
provlake/persistence/managed_persister.py
provlake/persistence/persister.py
provlake/persistence/unmanaged_persister.py
provlake/prospective/__init__.py
provlake/prospective/data_store_catalog.py
provlake/utils/__init__.py
provlake/utils/args_handler.py
provlake/utils/constants.py
provlake/utils/prov_utils.py
provlake/utils/sample_extraction_functions.py
provlake-0.2.982.dist-info/LICENSE
provlake-0.2.982.dist-info/METADATA
provlake-0.2.982.dist-info/WHEEL
provlake-0.2.982.dist-info/top_level.txt
provlake-0.2.982.dist-info/RECORD
