Metadata-Version: 2.1
Name: provlake
Version: 0.2.982
Summary: A Python lib to capture multiworkflow provenance data
Home-page: http://ibm.biz/provlake
Author: IBM Research
Author-email: rfsouza@br.ibm.com
License: Apache 2.0
Platform: UNKNOWN
Requires-Python: >=3.6,<3.9
License-File: LICENSE
Requires-Dist: requests-futures
Requires-Dist: numpy
Requires-Dist: pandas
